tweets_scraper.py
tweets_scraper-0.0.6.dist-info/METADATA
tweets_scraper-0.0.6.dist-info/WHEEL
tweets_scraper-0.0.6.dist-info/top_level.txt
tweets_scraper-0.0.6.dist-info/RECORD
